oscarapicheckout/__init__.py
oscarapicheckout/apps.py
oscarapicheckout/cache.py
oscarapicheckout/email.py
oscarapicheckout/fraud.py
oscarapicheckout/handlers.py
oscarapicheckout/methods.py
oscarapicheckout/mixins.py
oscarapicheckout/permissions.py
oscarapicheckout/py.typed
oscarapicheckout/serializers.py
oscarapicheckout/settings.py
oscarapicheckout/signals.py
oscarapicheckout/states.py
oscarapicheckout/utils.py
oscarapicheckout/views.py
oscarapicheckout/locale/es/LC_MESSAGES/django.mo
oscarapicheckout/locale/es/LC_MESSAGES/django.po
oscarapicheckout/tests/__init__.py
oscarapicheckout/tests/base.py
oscarapicheckout/tests/test_cache.py
oscarapicheckout/tests/test_checkout.py
oscarapicheckout/tests/test_fraud.py
oscarapicheckout/tests/test_methods.py
oscarapicheckout/tests/test_payment_method_introspection.py
oscarapicheckout/tests/test_permissions.py
django_oscar_api_checkout-3.8.0.dist-info/METADATA
django_oscar_api_checkout-3.8.0.dist-info/WHEEL
django_oscar_api_checkout-3.8.0.dist-info/licenses/LICENSE
django_oscar_api_checkout-3.8.0.dist-info/RECORD
