Metadata-Version: 2.4
Name: django-oscar-api-checkout
Version: 3.8.0
Summary: An extension on top of django-oscar-api providing a more flexible checkout API with a pluggable payment methods interface.
Project-URL: Homepage, https://gitlab.com/thelabnyc/django-oscar/django-oscar-api-checkout
Project-URL: Repository, https://gitlab.com/thelabnyc/django-oscar/django-oscar-api-checkout
Author-email: thelab <thelabdev@thelab.co>
License: ISC
License-File: LICENSE
Requires-Python: >=3.12
Requires-Dist: django-oscar-api==3.3.0
Requires-Dist: django-oscar<4.1,>=4.0
Requires-Dist: django>=4.2
Requires-Dist: drf-recaptcha<5,>=4.0.2
